dans/__init__.py
dans/data/bball-ref-teams.csv
dans/data/cache.csv
dans/data/nba-stats-teams.csv
dans/data/player_ids.csv
dans/data/player_names.csv
dans/data/season-averages.csv
dans/endpoints/__init__.py
dans/endpoints/_base.py
dans/endpoints/boxscore/__init__.py
dans/endpoints/boxscore/bxplayerlogs.py
dans/endpoints/boxscore/bxplayerstats.py
dans/endpoints/boxscore/bxteams.py
dans/endpoints/playbyplay/__init__.py
dans/endpoints/playbyplay/pbpplayerlogs.py
dans/endpoints/playbyplay/pbpplayerstats.py
dans/library/__init__.py
dans/library/bx_counter.py
dans/library/bx_possessions.py
dans/library/cache.py
dans/library/constants.py
dans/library/nba_api_client.py
dans/library/parameters.py
dans/library/pbp_counter.py
dans/library/pbp_processor.py
dans/library/stats_engine.py
dans/library/request/base.py
dans/library/request/basketball_reference.py
dans/library/request/data_sources.py
dans/library/request/nba_stats.py
dans/library/request/request.py
dans/library/request/request_params.py
dans/library/request/cache/cached_args.py
dans/library/request/cache/mock_response.py
dans/library/request/cache/data/KAJ1974BX.txt
dans/library/request/cache/data/KB2003.txt
dans/library/request/cache/data/KB2003BX.txt
dans/library/request/cache/data/KB2003G1_gr_1.txt
dans/library/request/cache/data/KB2003G1_gr_2.txt
dans/library/request/cache/data/KB2003G1_pbpv2_1.txt
dans/library/request/cache/data/KB2003G1_pbpv2_2.txt
dans/library/request/cache/data/KB2003G1_pbpv3_1.txt
dans/library/request/cache/data/KB2003G1_pbpv3_2.txt
dans/library/request/cache/data/KB2003G2_gr_1.txt
dans/library/request/cache/data/KB2003G2_gr_2.txt
dans/library/request/cache/data/KB2003G2_pbpv2_1.txt
dans/library/request/cache/data/KB2003G2_pbpv2_2.txt
dans/library/request/cache/data/KB2003G2_pbpv3_1.txt
dans/library/request/cache/data/KB2003G2_pbpv3_2.txt
dans/library/request/cache/data/KB2003G3_gr_1.txt
dans/library/request/cache/data/KB2003G3_gr_2.txt
dans/library/request/cache/data/KB2003G3_pbpv2_1.txt
dans-1.1.2.dist-info/METADATA
dans-1.1.2.dist-info/WHEEL
dans-1.1.2.dist-info/licenses/LICENSE
dans-1.1.2.dist-info/RECORD
