Metadata-Version: 2.4
Name: dans
Version: 1.1.2
Dynamic: Keywords
Dynamic: License
Dynamic: License-Expression
Summary: A package for scraping data from basketball-reference.com and stats.nba.com to provide opponent-adjusted statistics.
Author-email: Oscar Gutierrez Altamirano <oscargutierreza617@gmail.com>
License-File: LICENSE
Classifier: License :: OSI Approved :: MIT License
Classifier: Operating System :: OS Independent
Classifier: Programming Language :: Python :: 3
Requires-Python: >=3.10
Requires-Dist: bs4>=0.0.2
Requires-Dist: build>=1.2.2.post1
Requires-Dist: lxml>=5.3.1
Requires-Dist: nba-api>=1.10.0
Requires-Dist: numpy>=2.2.3
Requires-Dist: pandas>=2.2.3
Requires-Dist: pylint>=3.3.5
Requires-Dist: pytest>=7.4.0
Requires-Dist: ratelimit>=2.2.1
Requires-Dist: requests>=2.32.3
Requires-Dist: six>=1.16.0
Requires-Dist: tqdm>=4.66.2
Requires-Dist: unidecode>=1.3.8
